[{"artist":"24kGoldn"},
{"artist":"Ariana Grande"},
{"artist":"Arizona Zervas"},
{"artist":"BENEE"},
{"artist":"BTS"},
{"artist":"Bad Bunny"},
{"artist":"Billie Eilish"},
{"artist":"Black Eyed Peas"},
{"artist":"Cardi B"},
{"artist":"DaBaby"},
{"artist":"Doja Cat"},
{"artist":"Drake"},
{"artist":"Dua Lipa"},
{"artist":"Eminem"},
{"artist":"Future"},
{"artist":"Harry Styles"},
{"artist":"JP Saxe"},
{"artist":"Jawsh 685"},
{"artist":"Juice WRLD"},
{"artist":"Justin Bieber"},
{"artist":"KAROL G"},
{"artist":"Lady Gaga"},
{"artist":"Lewis Capaldi"},
{"artist":"Lil Mosey"},
{"artist":"Maluma"},
{"artist":"Maroon 5"},
{"artist":"Post Malone"},
{"artist":"Powfu"},
{"artist":"Regard"},
{"artist":"Roddy Ricch"},
{"artist":"SAINt JHN"},
{"artist":"Shawn Mendes"},
{"artist":"Surf Mesa"},
{"artist":"Surfaces"},
{"artist":"THE SCOTTS"},
{"artist":"The Weeknd"},
{"artist":"Tones And I"},
{"artist":"Topic"},
{"artist":"Travis Scott"},
{"artist":"Trevor Daniel"}]
